evo_django_kits/__init__.py
evo_django_kits/__main__.py
evo_django_kits/base.py
evo_django_kits/cli.py
evo_django_kits/settings.py
evo_django_kits/django_moduler/__init__.py
evo_django_kits/django_moduler/evo_router.py
evo_django_kits/django_moduler/rest_framework.py
evo_django_kits/entities/__init__.py
evo_django_kits/entities/base_viewset.py
evo_django_kits/entities/evo_response.py
evo_django_kits/entities/pagination/__init__.py
evo_django_kits/entities/pagination/evo_page_number_pagination.py
evo_django_kits/entities/permissions/__init__.py
evo_django_kits/entities/permissions/is_staff.py
evo_django_kits/entities/permissions/is_staff_or_read_only.py
evo_django_kits/entities/serializers/__init__.py
evo_django_kits/entities/serializers/bulk_delete_serializer.py
evo_django_kits-0.1.1.dist-info/licenses/LICENSE
evo_django_kits-0.1.1.dist-info/METADATA
evo_django_kits-0.1.1.dist-info/WHEEL
evo_django_kits-0.1.1.dist-info/entry_points.txt
evo_django_kits-0.1.1.dist-info/top_level.txt
evo_django_kits-0.1.1.dist-info/RECORD
