Metadata-Version: 2.4
Name: evo_django_kits
Version: 0.1.1
Summary: Awesome evo_django_kits created by maycuatroi
Home-page: https://github.com/maycuatroi/evo-django-kits/
Author: maycuatroi
License-File: LICENSE
Requires-Dist: django
Requires-Dist: python-dotenv
Requires-Dist: loguru
Requires-Dist: django-filter
Provides-Extra: test
Requires-Dist: pytest; extra == "test"
Requires-Dist: coverage; extra == "test"
Requires-Dist: flake8; extra == "test"
Requires-Dist: black; extra == "test"
Requires-Dist: isort; extra == "test"
Requires-Dist: pytest-cov; extra == "test"
Requires-Dist: codecov; extra == "test"
Requires-Dist: mypy; extra == "test"
Requires-Dist: gitchangelog; extra == "test"
Requires-Dist: mkdocs; extra == "test"
Requires-Dist: GitPython; extra == "test"
Dynamic: author
Dynamic: description
Dynamic: description-content-type
Dynamic: home-page
Dynamic: license-file
Dynamic: provides-extra
Dynamic: requires-dist
Dynamic: summary
